gumc.py
gumd.py
gumd-0.0.21.data/scripts/gumc
gumd-0.0.21.data/scripts/gumd
gumd-0.0.21.dist-info/METADATA
gumd-0.0.21.dist-info/WHEEL
gumd-0.0.21.dist-info/top_level.txt
gumd-0.0.21.dist-info/RECORD
