Metadata-Version: 2.1
Name: gumd
Version: 0.0.21
Summary: gumd, Grande Unified Multicast Daemon
Home-page: https://github.com/futzu/gumd
Author: Adrian
Author-email: spam@iodisco.com
Platform: all
Classifier: License :: OSI Approved :: MIT License
Classifier: Operating System :: OS Independent
Classifier: Programming Language :: Python :: 3.6
Classifier: Programming Language :: Python :: Implementation :: PyPy
Classifier: Programming Language :: Python :: Implementation :: CPython
Requires-Python: >=3.6
Requires-Dist: new-reader (>=0.1.07)
